{
    "Heren A Selectie": [
        "Jim Visser",
        "Mohammed Azaroiali",
        "Floris van Bemmelen",
        "Sergio Bhugwandass",
        "Lennart Cok",
        "Nino Jonkman",
        "Abdelhak Ouled Said"
    ],
    "Heren B Selectie": [
        "Dennis Immerzeel",
        "Bram Bahnerth",
        "Huub Bahnerth",
        "Eddy al Bazze",
        "Coen Pothof"
    ],
    "Vrouwen A Selectie": [
        "Femke van der Burg",
        "Jonna Hulshof",
        "Donna de Vos",
        "Naomi Jonkman",
        "Sasha Leemans",
        "Peta Houting"
    ],
    "Vrouwen B Selectie": [
        "Dana Schapendonk",
        "Lieve Legel",
        "Inez Meijer",
        "Bente Vuurman",
        "Nienke Spijker",
        "Elise Parren",
        "Esmee van der Burg",
        "Lotte Trouwborst"
    ],
    "JO7": [
        "Kjeld Bes",
        "Julian Giesbers",
        "Evan Quinn Koster",
        "Jens Vonk"
    ],
    "JO8-1": [
        "Noor-Farah Zaidouni",
        "Bence Hanyu"
    ],
    "JO8-2": [
        "Tijs Bosman",
        "Rohan Khoesial",
        "D\u00eavy Nguyen"
    ],
    "JO8-3": [
        "Cas van den Berg"
    ],
    "JO8-4": [
        "Eloise Hoogendoorn",
        "Sofie Bertens",
        "Kaj Koopman",
        "Kris van der Velden"
    ],
    "JO8-5": [
        "Raya\u00eblla Lopes",
        "Vin Payothornsiri",
        "Anna Roelofsen",
        "Elisa Sewrajsing"
    ],
    "JO8-6": [
        "Adam-Blue Kooijman"
    ],
    "JO8-7": [
        "Bo Hermus",
        "Gijs van Daalen"
    ],
    "JO9-1": [
        "Joep Sonneveld",
        "Tommy de Vogel"
    ],
    "JO9-2": [
        "Jesse Schrammeijer",
        "Robin Smid",
        "Julian Zoeteman"
    ],
    "JO9-3": [
        "Aron Riemens",
        "Job van Rijn"
    ],
    "JO9-4": [
        "Mohamed Rayan Kahi",
        "Mees van der Loo",
        "Tom van der Sluis"
    ],
    "JO9-5": [
        "Olivier Blok",
        "Pepijn Donkersloot",
        "Yvo Haket",
        "Karlijn van Hout"
    ],
    "JO9-6": [
        "Neve B\u00e9r\u00e9nos",
        "Evi van der Plas",
        "Daphne Rijckborst",
        "Victor van de Ven"
    ],
    "JO9-7": [
        "Jack Hofman"
    ],
    "JO10-1": [
        "Sven Blanc",
        "Thomas Bredemeijer",
        "Sam Kennepohl"
    ],
    "JO10-2": [
        "Gijs de Groot"
    ],
    "JO10-3": [
        "Brando van Belle",
        "Kay Molenaar",
        "Dex Verhagen"
    ],
    "JO10-4": [
        "Olivier Flink",
        "C\u00e9dric van Wezel"
    ],
    "JO10-5": [
        "Jack Peeters"
    ],
    "JO10-6": [
        "Sem Wilson"
    ],
    "JO10-7": [
        "Elias van Scheijndel"
    ],
    "JO10-8": [
        "Aethan van Breda",
        "Sophie Veenman"
    ],
    "JO10-9": [
        "Amnet Bokuretsion",
        "Aryan Ponath Akhilesh"
    ],
    "JO11-1": [],
    "JO11-2": [
        "Julian van Hattem",
        "Benyamin Redjosentono"
    ],
    "JO11-3": [
        "Milan Wesdorp"
    ],
    "JO11-4": [
        "Julia Clarijs",
        "Marit van der Gaag",
        "Star Rutten"
    ],
    "JO11-5": [
        "Sami Berri",
        "Isa van Dijk"
    ],
    "JO11-6": [
        "Faris Lahlou"
    ],
    "JO11-7": [
        "Bas Vliegenthart",
        "Younes El-ghabi",
        "Lot Ligtvoet",
        "Lynn Vermeulen"
    ],
    "JO11-8": [],
    "JO12-1": [
        "Mohamed Kaddouri",
        "Benjamin Kraan",
        "Yves Lock"
    ],
    "JO12-2": [
        "Juul van Kleeff",
        "Pim Wisgerhof"
    ],
    "JO12-3": [
        "Lucas Lous"
    ],
    "JO12-4": [
        "Tess den Hollander"
    ],
    "JO12-5": [],
    "JO12-6": [],
    "MO12-1": [
        "Bo de Goede",
        "Damla Bagcan",
        "Pippa van Muijen",
        "Kelsey Pijpers",
        "Lise Reijnhoudt"
    ],
    "JO13-1": [
        "Mats Hulst",
        "Zino van der Linden",
        "Thom Star",
        "Tim Stavorinus",
        "George de Veld"
    ],
    "JO13-2": [
        "Benjamin van der Wal",
        "Femke Ammerlaan",
        "Willem van Etten",
        "Feline de Haan",
        "Jesper Post",
        "Bo van der Sande",
        "Vince Verzaal",
        "Yassin Yaqoubi",
        "Luca Zoeteweij"
    ],
    "JO13-3": [
        "Thijmen Eggink",
        "Tom Pannekoek",
        "Julian Vonk",
        "Tim van de Watering"
    ],
    "JO13-4": [
        "Tristan Buningh",
        "Tijs van den Berg",
        "Kevin Hillebrand",
        "Jurre van Schie",
        "Alex Zentjens"
    ],
    "JO13-5": [
        "Tim Evers",
        "Stijn Potharst"
    ],
    "MO13-1": [
        "Felicia Bello",
        "Jula de Bode",
        "Cheyenne Otto"
    ],
    "JO14-1": [
        "Milan Krab",
        "Dani Domic",
        "Yannick Smeets"
    ],
    "JO14-2": [
        "Matthijs Bredemeijer",
        "Kate van Nierop"
    ],
    "JO14-3": [
        "Koen Huizinga",
        "Jez Vols"
    ],
    "JO14-4": [
        "Thomas Bhagwandin",
        "Nasim Elmaachi",
        "Tim Steenbergen"
    ],
    "JO14-5": [
        "Noah Hollander"
    ],
    "JO15-1": [
        "Laurens Boot",
        "Jake Kroon",
        "Jelte van Schie",
        "Roel Stolk",
        "Nick Verzaal",
        "Scott Vonk",
        "Sten Wijgh"
    ],
    "JO15-3": [
        "Kerim Albayrak",
        "Dax Brand",
        "Abel van Ingen",
        "Yeon Joon Kim",
        "Mathieu van de Woestijne"
    ],
    "MO15-1": [
        "Nikki Desserjer",
        "Isabella Goosen",
        "Nova Kalker",
        "Mayuri Streefland"
    ],
    "MO15-2": [
        "Inge van Dijk",
        "Chelsea Hennevanger"
    ],
    "JO16-1": [
        "Sam Storm",
        "Enza Cassa",
        "Bas Klop",
        "Stijn van Leeuwen"
    ],
    "JO16-2": [
        "Daniel Bhagwandin",
        "Samuel Buitelaar",
        "Joaquin van Lingen",
        "Evan Schalker",
        "Jasper Schram"
    ],
    "JO17-1": [
        "Samuel Oost",
        "Wes Vonk",
        "Zanyar Zeno"
    ],
    "JO17-2": [
        "Fynn Verhagen",
        "Mika Langelaan",
        "Finn Duymaer van Twist",
        "Sem IJzermans"
    ],
    "JO17-3": [
        "Walid Alsalkhadi",
        "Milo van der Heijden",
        "Ruben Postema",
        "Abel Stuijt",
        "Gyon Thiel"
    ],
    "MO17-1": [
        "Annalie de Boer",
        "Anastacia Hiwat",
        "Lotte van Ingen",
        "Emi Maasland",
        "Fien Torn"
    ],
    "MO17-2": [
        "Tessa van der Velden"
    ],
    "MO17-3": [
        "Lucille ter Heijden",
        "Anouk Klop"
    ],
    "JO19-1": [
        "Tim Bloot",
        "Thijs Bossche",
        "Damian Bruin",
        "Tim Clarijs",
        "Boris Gilhuijs",
        "Leonard Mewe",
        "Milan de Vos",
        "Sven Wiebenga"
    ],
    "JO19-2": [
        "Dani\u00ebl Bus\u00e9",
        "Rick Meegdes",
        "Dimes Yany"
    ],
    "JO19-3": [
        "Sil Bork",
        "Liam Labordus",
        "Thijs van Leeuwen"
    ],
    "MO20-1": [
        "Charlotte de Groot"
    ]
}